[
  {
    "id": 0,
    "file": "bronte-s",
    "name": "Bronte Beach"
  },
  {
    "id": 1,
    "file": "gordons",
    "name": "Gordons Bay"
  },
  {
    "id": 2,
    "file": "bronte-n",
    "name": "Bronte Beach"
  },
  {
    "id": 3,
    "file": "clovelly",
    "name": "Clovelly Beach"
  },
  {
    "id": 4,
    "file": "tamarama",
    "name": "Tamarama Beach"
  },
  {
    "id": 5,
    "file": "coogee",
    "name": "Coogee Beach"
  },
  {
    "id": 6,
    "file": "bondi-s",
    "name": "Bondi Beach"
  },
  {
    "id": 7,
    "file": "bondi-n",
    "name": "Bondi Beach"
  },
  {
    "id": 8,
    "file": "mackenzies",
    "name": "Mackenzies Bay"
  }
]
